bermuda/__init__.py
bermuda/_bermuda.cp314-win_arm64.pyd
bermuda/_bermuda.pyi
bermuda/_version.py
bermuda-0.1.6.dist-info/licenses/LICENSE
bermuda-0.1.6.dist-info/METADATA
bermuda-0.1.6.dist-info/WHEEL
bermuda-0.1.6.dist-info/top_level.txt
bermuda-0.1.6.dist-info/RECORD
