Metadata-Version: 2.4
Name: bermuda
Version: 0.1.6
Summary: Spatial algorithms for napari project, compiled for performance
License-Expression: BSD-3-Clause
Project-URL: Bug Tracker, https://github.com/napari/bermuda/issues
Project-URL: Documentation, https://github.com/napari/bermuda/blob/main/README.md
Project-URL: Source Code, https://github.com/napari/bermuda
Classifier: Development Status :: 3 - Alpha
Classifier: Operating System :: OS Independent
Classifier: Programming Language :: Python :: 3
Classifier: Programming Language :: Python :: 3 :: Only
Classifier: Programming Language :: Python :: 3.9
Classifier: Programming Language :: Python :: 3.10
Classifier: Programming Language :: Python :: 3.11
Classifier: Programming Language :: Python :: 3.12
Classifier: Programming Language :: Python :: 3.13
Classifier: Programming Language :: Python :: 3.14
Classifier: Programming Language :: Rust
Classifier: Programming Language :: Python :: Implementation :: CPython
Classifier: Topic :: Scientific/Engineering :: Bio-Informatics
Requires-Python: >=3.9
License-File: LICENSE
Requires-Dist: numpy>=1.22.2
Dynamic: license-file
